ansys/modelcenter/workflow/__init__.py
ansys/modelcenter/workflow/api/__init__.py
ansys/modelcenter/workflow/api/iassembly.py
ansys/modelcenter/workflow/api/ibooleanarraydatapin.py
ansys/modelcenter/workflow/api/ibooleandatapin.py
ansys/modelcenter/workflow/api/icomponent.py
ansys/modelcenter/workflow/api/idatapin.py
ansys/modelcenter/workflow/api/idatapin_link.py
ansys/modelcenter/workflow/api/idatapinreferencebase.py
ansys/modelcenter/workflow/api/idrivercomponent.py
ansys/modelcenter/workflow/api/iengine.py
ansys/modelcenter/workflow/api/ifilearraydatapin.py
ansys/modelcenter/workflow/api/ifiledatapin.py
ansys/modelcenter/workflow/api/iformat.py
ansys/modelcenter/workflow/api/igroup.py
ansys/modelcenter/workflow/api/iintegerarraydatapin.py
ansys/modelcenter/workflow/api/iintegerdatapin.py
ansys/modelcenter/workflow/api/irealarraydatapin.py
ansys/modelcenter/workflow/api/irealdatapin.py
ansys/modelcenter/workflow/api/ireferencearraydatapin.py
ansys/modelcenter/workflow/api/ireferencedatapin.py
ansys/modelcenter/workflow/api/ireferenceproperty.py
ansys/modelcenter/workflow/api/irenamable_elements.py
ansys/modelcenter/workflow/api/istringarraydatapin.py
ansys/modelcenter/workflow/api/istringdatapin.py
ansys/modelcenter/workflow/api/iworkflow.py
ansys/modelcenter/workflow/grpc_modelcenter/__init__.py
ansys/modelcenter/workflow/grpc_modelcenter/abstract_assembly_child.py
ansys/modelcenter/workflow/grpc_modelcenter/abstract_control_statement.py
ansys/modelcenter/workflow/grpc_modelcenter/abstract_datapin_container.py
ansys/modelcenter/workflow/grpc_modelcenter/abstract_renamable.py
ansys/modelcenter/workflow/grpc_modelcenter/abstract_workflow_element.py
ansys/modelcenter/workflow/grpc_modelcenter/assembly.py
ansys/modelcenter/workflow/grpc_modelcenter/base_datapin.py
ansys/modelcenter/workflow/grpc_modelcenter/boolean_datapin.py
ansys/modelcenter/workflow/grpc_modelcenter/component.py
ansys/modelcenter/workflow/grpc_modelcenter/create_datapin.py
ansys_modelcenter_workflow-0.1.2.dist-info/licenses/LICENSE
ansys_modelcenter_workflow-0.1.2.dist-info/WHEEL
ansys_modelcenter_workflow-0.1.2.dist-info/METADATA
ansys_modelcenter_workflow-0.1.2.dist-info/RECORD
