Metadata-Version: 2.4
Name: ansys-modelcenter-workflow
Version: 0.1.2
Summary: A python wrapper for ModelCenter Desktop
Author-email: "ANSYS, Inc." <pyansys.core@ansys.com>
Maintainer-email: "ANSYS, Inc." <pyansys.core@ansys.com>
Requires-Python: >=3.10,<4
Classifier: Development Status :: 4 - Beta
Classifier: License :: OSI Approved :: MIT License
Classifier: Operating System :: Microsoft :: Windows :: Windows 7
Classifier: Operating System :: Microsoft :: Windows :: Windows Vista
Classifier: Operating System :: Microsoft :: Windows :: Windows 8
Classifier: Operating System :: Microsoft :: Windows :: Windows 8.1
Classifier: Operating System :: Microsoft :: Windows :: Windows 10
Classifier: Operating System :: Microsoft :: Windows :: Windows 11
Classifier: Operating System :: Microsoft :: Windows :: Windows Server 2003
Classifier: Operating System :: Microsoft :: Windows :: Windows Server 2008
Classifier: Programming Language :: Python :: 3.10
Classifier: Programming Language :: Python :: 3.11
Classifier: Programming Language :: Python :: 3.12
Classifier: Programming Language :: Python :: 3.13
License-File: LICENSE
Requires-Dist: ansys-platform-instancemanagement>=1.1.1
Requires-Dist: ansys-api-modelcenter>=0.3.1
Requires-Dist: numpy>=1.22.3
Requires-Dist: overrides>=6.1
Requires-Dist: pyansys-tools-variableinterop>=0.1.2
Requires-Dist: protobuf>=5.29.2
Requires-Dist: ansys-engineeringworkflow-api>=0.1.1
Requires-Dist: ansys-tools-common>=0.4.0
Requires-Dist: ansys-engineeringworkflow-api==0.1.1 ; extra == "doc"
Requires-Dist: ansys-sphinx-theme[autoapi]==1.6.4 ; extra == "doc"
Requires-Dist: numpydoc==1.10.0 ; extra == "doc"
Requires-Dist: pyansys-tools-variableinterop==0.1.2 ; extra == "doc"
Requires-Dist: pytest-sphinx==0.6.3 ; extra == "doc"
Requires-Dist: sphinx==8.2.3 ; extra == "doc"
Requires-Dist: sphinx-copybutton==0.5.2 ; extra == "doc"
Requires-Dist: sphinx-gallery==0.20.0 ; extra == "doc"
Requires-Dist: sphinx-notfound-page==1.1.0 ; extra == "doc"
Requires-Dist: ansys-engineeringworkflow-api==0.1.1 ; extra == "tests"
Requires-Dist: grpcio==1.76.0 ; extra == "tests"
Requires-Dist: pyansys-tools-variableinterop==0.1.2 ; extra == "tests"
Requires-Dist: pytest==9.0.1 ; extra == "tests"
Requires-Dist: pytest-cov==7.0.0 ; extra == "tests"
Project-URL: Discussions, https://github.com/ansys/pymodelcenter/discussions
Project-URL: Documentation, https://modelcenter.docs.pyansys.com
Project-URL: Issues, https://github.com/ansys/pymodelcenter/issues
Project-URL: Releases, https://github.com/ansys/pymodelcenter/releases
Project-URL: Source, https://github.com/ansys/pymodelcenter
Provides-Extra: doc
Provides-Extra: tests
